MANIFEST.in
README.rst
VERSION
setup.py
unixpackage/__init__.py
unixpackage/api.py
unixpackage/commandline.py
unixpackage/exceptions.py
unixpackage/package_group.py
unixpackage/utils.py
unixpackage.egg-info/PKG-INFO
unixpackage.egg-info/SOURCES.txt
unixpackage.egg-info/dependency_links.txt
unixpackage.egg-info/entry_points.txt
unixpackage.egg-info/not-zip-safe
unixpackage.egg-info/top_level.txt
unixpackage/click/__init__.py
unixpackage/click/_bashcomplete.py
unixpackage/click/_compat.py
unixpackage/click/_termui_impl.py
unixpackage/click/_textwrap.py
unixpackage/click/core.py
unixpackage/click/decorators.py
unixpackage/click/exceptions.py
unixpackage/click/formatting.py
unixpackage/click/globals.py
unixpackage/click/parser.py
unixpackage/click/termui.py
unixpackage/click/testing.py
unixpackage/click/types.py
unixpackage/click/utils.py