Metadata-Version: 1.1
Name: unixpackage
Version: 0.4.1
Summary: One command to install equivalent packages in Ubuntu, Debian, CentOS, Fedora, Red Hat and Mac OS X.
Home-page: https://github.com/unixpackage/unixpackage
Author: Colm O'Connor
Author-email: colm.oconnor.github@gmail.com
License: AGPL
Keywords: apt-get yum brew mac dpkg rpm unix package finder
Platform: UNKNOWN
Classifier: Development Status :: 3 - Alpha
Classifier: Intended Audience :: Developers
Classifier: License :: OSI Approved :: GNU Affero General Public License v3 or later (AGPLv3+)
Classifier: Operating System :: Unix
Classifier: Environment :: Console
Classifier: Programming Language :: Python :: 2
Classifier: Programming Language :: Python :: 2.6
Classifier: Programming Language :: Python :: 2.7
Classifier: Programming Language :: Python :: 3
Classifier: Programming Language :: Python :: 3.4
